LICENSE.txt
README.md
pyproject.toml
setup.cfg
setup.py
src/stormkitty/__init__.py
src/stormkitty/skgen.py
src/stormkitty.egg-info/PKG-INFO
src/stormkitty.egg-info/SOURCES.txt
src/stormkitty.egg-info/dependency_links.txt
src/stormkitty.egg-info/requires.txt
src/stormkitty.egg-info/top_level.txt